docs/__init__.py
pydgc/__init__.py
pydgc/clusterings/__init__.py
pydgc/clusterings/batch_kmeans_gpu.py
pydgc/clusterings/kmeans_gpu.py
pydgc/datasets/__init__.py
pydgc/datasets/utils.py
pydgc/metrics/__init__.py
pydgc/metrics/utils.py
pydgc/models/__init__.py
pydgc/models/ae.py
pydgc/models/agcdrr.py
pydgc/models/ccgc.py
pydgc/models/daegc.py
pydgc/models/dcrn.py
pydgc/models/dfcn.py
pydgc/models/dgc_model.py
pydgc/models/dgcluster.py
pydgc/models/gae.py
pydgc/models/gae_ssc.py
pydgc/models/hsan.py
pydgc/models/magi.py
pydgc/models/magi_batch.py
pydgc/models/ns4gc.py
pydgc/models/sdcn.py
pydgc/modules/__init__.py
pydgc/modules/decoder.py
pydgc/modules/encoder.py
pydgc/modules/ssc.py
pydgc/modules/utils.py
pydgc/pipelines/__init__.py
pydgc/pipelines/agcdrr_pipeline.py
pydgc/pipelines/base_pipeline.py
pydgc/pipelines/ccgc_pipeline.py
pydgc/pipelines/daegc_pipeline.py
pydgc/pipelines/dcrn_pipeline.py
pydgc/pipelines/dfcn_pipeline.py
pydgc/pipelines/dgcluster_pipeline.py
pydgc/pipelines/gae_pipeline.py
pydgc/pipelines/gae_ssc_pipeline.py
pydgc/pipelines/hsan_pipeline.py
pydgc/pipelines/magi_batch_pipeline.py
pydgc/pipelines/magi_pipeline.py
pydgc/pipelines/ns4gc_pipeline.py
pydgc/pipelines/sdcn_pipeline.py
pydgc/utils/__init__.py
pydgc/utils/command.py
pydgc/utils/config.py
pydgc/utils/device.py
pydgc/utils/logger.py
pydgc/utils/random.py
pydgc/utils/transform.py
pydgc/utils/visualization.py
pydgc-1.0.3.dist-info/LICENSE
pydgc-1.0.3.dist-info/METADATA
pydgc-1.0.3.dist-info/WHEEL
pydgc-1.0.3.dist-info/top_level.txt
pydgc-1.0.3.dist-info/RECORD
