Metadata-Version: 2.1
Name: pydgc
Version: 1.0.3
Summary: PyDGC: A Deep Graph Clustering Benchmark
Home-page: https://github.com/Marigoldwu/PyDGC
Author: Benyu Wu
Author-email: bywu109@163.com
Project-URL: Bug Tracker, https://github.com/Marigoldwu/PyDGC/issues
Keywords: Deep Graph Clustering,Deep Clustering,PyTorch,PyG
Classifier: Programming Language :: Python :: 3
Classifier: License :: OSI Approved :: MIT License
Classifier: Operating System :: OS Independent
Requires-Python: >=3.8
License-File: LICENSE
Requires-Dist: matplotlib>=3.7.5
Requires-Dist: numpy>=1.24.1
Requires-Dist: ogb>=1.3.6
Requires-Dist: PyYAML>=6.0.1
Requires-Dist: rich>=14.0.0
Requires-Dist: scikit-learn>=1.3.2
Requires-Dist: scipy>=1.9.1
Requires-Dist: seaborn>=0.13.2
Requires-Dist: setuptools>=68.2.2
Requires-Dist: torch>=2.0.0
Requires-Dist: torch-cluster>=1.6.2
Requires-Dist: torch-geometric>=2.5.1
Requires-Dist: torch-sparse>=0.6.18
Requires-Dist: torch-scatter>=2.1.2
Requires-Dist: umap-learn>=0.5.7
Requires-Dist: yacs>=0.1.8
